telegram_interface_cli/__init__.py
telegram_interface_cli/__name__.py
telegram_interface_cli/__version__.py
telegram_interface_cli/config.py
telegram_interface_cli/exceptions.py
telegram_interface_cli/logger.py
telegram_interface_cli/telegram_interface_cli.py
telegram_interface_cli-0.1.7.data/scripts/telegram-interface
tests/__init__.py
tests/test_telegram_interface_cli.py
telegram_interface_cli-0.1.7.dist-info/LICENSE
telegram_interface_cli-0.1.7.dist-info/METADATA
telegram_interface_cli-0.1.7.dist-info/WHEEL
telegram_interface_cli-0.1.7.dist-info/top_level.txt
telegram_interface_cli-0.1.7.dist-info/RECORD
