Metadata-Version: 2.1
Name: telegram-interface-cli
Version: 0.1.7
Summary: A quick tool for listing the Telegram Messenger groups that a user is within.
Home-page: https://github.com/ndejong/telegram-interface
Author: Nicholas de Jong
Author-email: contact@nicholasdejong.com
License: BSD 2-Clause
Keywords: telegram telegram-group
Platform: UNKNOWN
Classifier: Intended Audience :: System Administrators
Classifier: Intended Audience :: Information Technology
Classifier: Programming Language :: Python :: 3
Classifier: License :: OSI Approved :: BSD License
